{"@class":"Animation","id":{"uuid":"456411C3-B397-4639-ACEE-B19626E7A10E"},"tracks":[{"@class":"FloatBehaviorTrack","clips":[{"@class":"FloatBehaviorClip","beginTime":0,"duration":0,"script":"FloatValueBehaviorClipScript","behavior":{"@class":"FloatBezierBehavior","frames":[{"@class":"FloatBezierKeyFrame","formula":{"@class":"FloatExpressionFormula","expression":"0"},"time":0,"point1":{"values":[0.0,0.0]},"point2":{"values":[0.0,0.0]},"order":"linear","transition":true}]}}],"script":"FloatBehaviorTrackScript","accessor":"FloatVariableAccessor","attribute":"dx"}]}