{"@class":"TimeLineScript","id":{"uuid":"0B7BD998-58A9-4186-956A-4189BCF62F04"},"name":"TimeLineScript","enableOnAwake":false,"loop":false,"jumpToFirstFrameAtEnd":false,"speed":1.0,"weight":1.0,"loopStartTime":0,"loopDuration":0,"is_imported":false,"type":"user","scripts":{"@class":"StdListRuntimeScript","list":[{"@class":"AnimationScript","id":{"uuid":"B8B5387B-C2A2-4EC4-AE1D-43AE863BCC98"},"name":"AnimationScript","enableOnAwake":false,"OwnerLink":{"@class":"BindingLink","targetId":{"uuid":"C28EF209-A01B-4AAB-B472-7A06EF56C37A"},"targetRelativeAddress":{"@class":"NodeRelativeAddressBase","index":7,"name":"Ligthing-1","subaddress":{"@class":"NodeRelativeAddressBase","index":3,"name":"HelmetLighting:Lighting"}}},"animation":{"uuid":"D58B9874-594F-45DC-8244-83AD524EFE42"},"AnimationType":"object3D","is_imported":false,"isEnabled":true}]},"triggers":[{"@class":"AnimationTrigger","id":{"uuid":"9ABD4D60-E7E6-492B-982A-110B336035DD"},"ownerScriptId":{"uuid":"0B7BD998-58A9-4186-956A-4189BCF62F04"},"logicOperation":0,"resultType":0,"isInverted":false,"event":2,"bindingLink":{"@class":"BindingLink","targetId":{"uuid":"214B0206-F767-462C-A527-6273ADA54C36"}}}]}