{"@class":"TimeLineScript","id":{"uuid":"1D31A824-EE60-49BB-89A7-09E22BEB74C1"},"name":"TimeLineScript","enableOnAwake":false,"loop":true,"jumpToFirstFrameAtEnd":false,"speed":1.0,"weight":1.0,"loopStartTime":0,"loopDuration":0,"is_imported":false,"type":"user","scripts":{"@class":"StdListRuntimeScript","list":[{"@class":"AnimationScript","id":{"uuid":"A7F781BE-13E0-4C7F-83CF-96C37A5FF144"},"name":"AnimationScript","enableOnAwake":false,"OwnerLink":{"@class":"BindingLink","targetId":{"uuid":"E3A11DC8-89FE-4849-BE26-74309561EDAE"}},"animation":{"uuid":"94D33590-D199-4963-BC40-77C6A167CB80"},"AnimationType":"avar","is_imported":false,"isEnabled":true},{"@class":"AnimationScript","id":{"uuid":"452EC65D-8EA1-4D53-9E3D-8D7EB273D9D6"},"name":"AnimationScript","enableOnAwake":false,"OwnerLink":{"@class":"BindingLink","targetId":{"uuid":"98AF9E2F-5829-4802-AA21-6A27EC64E1E4"},"targetRelativeAddress":{"@class":"NodeRelativeAddressBase","index":2,"name":"Ligthing-1","subaddress":{"@class":"NodeRelativeAddressBase","index":3,"name":"HelmetLighting:Lighting"}}},"animation":{"uuid":"0013C9BB-54CB-441D-943B-2F436F6B60A6"},"AnimationType":"object3D","is_imported":false,"isEnabled":true}]},"triggers":[{"@class":"AnimationTrigger","id":{"uuid":"1A7AAB5A-6013-4A4B-9EEE-BCA4CAB8CD93"},"ownerScriptId":{"uuid":"1D31A824-EE60-49BB-89A7-09E22BEB74C1"},"logicOperation":0,"resultType":0,"isInverted":false,"event":3,"bindingLink":{"@class":"BindingLink","targetId":{"uuid":"436A11FB-BD60-4767-90E5-629E515F1ACF"}}}],"symbolTable":{"@class":"VariousSymbolTable","id":{"uuid":"5A93FD59-8A9F-4E20-BFCE-00170B8BFD8A"},"variables":[{"@class":"VariantVariable","id":{"uuid":"E3A11DC8-89FE-4849-BE26-74309561EDAE"},"name":"ry","type":"float","value":52.0}]}}