{"@class":"TimeLineScript","id":{"uuid":"30F1690E-CFB1-4EA6-A737-90EAC4F8FBB5"},"name":"TimeLineScript","enableOnAwake":false,"loop":true,"jumpToFirstFrameAtEnd":false,"speed":1.0,"weight":1.0,"loopStartTime":0,"loopDuration":0,"is_imported":false,"type":"user","scripts":{"@class":"StdListRuntimeScript","list":[{"@class":"AnimationScript","id":{"uuid":"BBC09795-0268-4E98-A371-4E8E76FC81AD"},"name":"AnimationScript","enableOnAwake":false,"OwnerLink":{"@class":"BindingLink","targetId":{"uuid":"15369B55-48A7-4A32-97D6-F669321BC111"},"targetRelativeAddress":{"@class":"NodeRelativeAddressBase","index":2,"name":"Light"}},"animation":{"uuid":"961A1862-37B9-4BCA-8E58-9F36BE00F9E8"},"AnimationType":"object3D","is_imported":false,"isEnabled":true}]},"triggers":[{"@class":"AnimationTrigger","id":{"uuid":"F0A765A1-3354-4138-8602-15887213A7B4"},"ownerScriptId":{"uuid":"30F1690E-CFB1-4EA6-A737-90EAC4F8FBB5"},"logicOperation":0,"resultType":0,"isInverted":false,"event":3,"bindingLink":{"@class":"BindingLink","targetId":{"uuid":"44013B97-B4C5-4828-976D-56E495B4D23F"}}}]}