{"@class":"TimeLineScript","id":{"uuid":"45B0B494-34BD-4BEE-BB2E-31808EFA2601"},"name":"TimeLineScript","enableOnAwake":false,"loop":false,"jumpToFirstFrameAtEnd":false,"speed":1.0,"weight":1.0,"loopStartTime":0,"loopDuration":0,"is_imported":false,"type":"user","scripts":{"@class":"StdListRuntimeScript","list":[{"@class":"AnimationScript","id":{"uuid":"C343C359-EB8C-42D8-9D06-CE59A3F5D41C"},"name":"AnimationScript","enableOnAwake":false,"OwnerLink":{"@class":"BindingLink","targetId":{"uuid":"FC2F52DB-0D2C-4B45-8FCC-A70263F77B0D"},"targetRelativeAddress":{"@class":"NodeRelativeAddressBase","index":6,"name":"Ligthing-1","subaddress":{"@class":"NodeRelativeAddressBase","index":3,"name":"HelmetLighting:Lighting"}}},"animation":{"uuid":"1ED5F50C-2EB8-4820-9C87-E4E8BBBB5F48"},"AnimationType":"object3D","is_imported":false,"isEnabled":true}]},"triggers":[{"@class":"AnimationTrigger","id":{"uuid":"E7F66558-7A2D-4145-9D56-27391D3E3AB9"},"ownerScriptId":{"uuid":"45B0B494-34BD-4BEE-BB2E-31808EFA2601"},"logicOperation":0,"resultType":0,"isInverted":false,"event":2,"bindingLink":{"@class":"BindingLink","targetId":{"uuid":"CFD19FED-55C0-46CB-82D5-D1E19AAE9BAE"}}}]}