{"@class":"TimeLineScript","id":{"uuid":"54A50A58-2AA0-4396-B8F5-A91C7029A370"},"name":"TimeLineScript","enableOnAwake":false,"loop":false,"jumpToFirstFrameAtEnd":false,"speed":1.0,"weight":1.0,"loopStartTime":0,"loopDuration":0,"is_imported":false,"type":"user","scripts":{"@class":"StdListRuntimeScript","list":[{"@class":"AnimationScript","id":{"uuid":"1D67D628-E4DB-4F9F-8032-E4407544A243"},"name":"AnimationScript","enableOnAwake":false,"OwnerLink":{"@class":"BindingLink","targetId":{"uuid":"C9C39101-6043-42A2-A39C-E1C1B086C323"},"targetRelativeAddress":{"@class":"NodeRelativeAddressBase","index":8,"name":"Ligthing-1","subaddress":{"@class":"NodeRelativeAddressBase","index":3,"name":"HelmetLighting:Lighting"}}},"animation":{"uuid":"73E279E4-AC6A-42A0-9D76-84CAC8F63A8A"},"AnimationType":"object3D","is_imported":false,"isEnabled":true}]},"triggers":[{"@class":"AnimationTrigger","id":{"uuid":"D6C12245-CC51-43EA-B37D-E516EA117A34"},"ownerScriptId":{"uuid":"54A50A58-2AA0-4396-B8F5-A91C7029A370"},"logicOperation":0,"resultType":0,"isInverted":false,"event":2,"bindingLink":{"@class":"BindingLink","targetId":{"uuid":"214B0206-F767-462C-A527-6273ADA54C36"}}}]}