{"@class":"TimeLineScript","id":{"uuid":"665FB5CA-151E-4BB2-A7B8-D47721654B67"},"name":"TimeLineScript","enableOnAwake":false,"loop":false,"jumpToFirstFrameAtEnd":false,"speed":1.0,"weight":1.0,"loopStartTime":0,"loopDuration":0,"is_imported":false,"type":"user","scripts":{"@class":"StdListRuntimeScript","list":[{"@class":"AnimationScript","id":{"uuid":"31C256F1-4751-47C9-93F1-B1CF9F02BCDB"},"name":"AnimationScript","enableOnAwake":false,"OwnerLink":{"@class":"BindingLink","targetId":{"uuid":"5E60F7DB-E878-4AC4-A2E1-350C6984C5DF"},"targetRelativeAddress":{"@class":"NodeRelativeAddressBase","index":40,"name":"Case 4"}},"animation":{"uuid":"34A00CCB-B7F6-4F05-A36A-FAE5ACDF1EF5"},"AnimationType":"object3D","is_imported":false,"isEnabled":true}]},"triggers":[{"@class":"AnimationTrigger","id":{"uuid":"77880928-A31A-407D-B6D0-F42770F181EB"},"ownerScriptId":{"uuid":"665FB5CA-151E-4BB2-A7B8-D47721654B67"},"logicOperation":0,"resultType":0,"isInverted":false,"event":2,"bindingLink":{"@class":"BindingLink","targetId":{"uuid":"CA270876-AA82-47B8-8497-DEFDDE246134"}}}]}