{"@class":"TimeLineScript","id":{"uuid":"792FA404-DF22-4EF2-B003-AE10D2F336E8"},"name":"Ray 1 Animation 1","enableOnAwake":false,"loop":false,"jumpToFirstFrameAtEnd":false,"speed":1.0,"weight":1.0,"loopStartTime":0,"loopDuration":0,"is_imported":false,"type":"user","scripts":{"@class":"StdListRuntimeScript","list":[{"@class":"AnimationScript","id":{"uuid":"B2A86FEF-AB2F-479B-860C-7559BBD40FCF"},"name":"Projectile_02","enableOnAwake":false,"OwnerLink":{"@class":"BindingLink","targetId":{"uuid":"273AF4F4-C58E-4C68-8259-3D36CD6FEB20"},"targetRelativeAddress":{"@class":"NodeRelativeAddressBase","index":0,"name":"Ray 2"}},"animation":{"uuid":"AC697DEE-EFC2-45FC-BBD2-3D2C1F141D44"},"AnimationType":"object3D","is_imported":false,"isEnabled":true}]},"triggers":[{"@class":"CollisionTrigger","id":{"uuid":"24D08B59-23C9-456B-99B2-11EBCC2CFBF2"},"ownerScriptId":{"uuid":"792FA404-DF22-4EF2-B003-AE10D2F336E8"},"logicOperation":0,"resultType":0,"isInverted":false,"eventType":"out","targetBindingLink":{"@class":"BindingLink","targetId":{"uuid":"75446D50-7F2C-4B5A-88D3-78248CA9A9E1"}},"zoneBindingLink":{"@class":"BindingLink","targetId":{"uuid":"200866DB-42CE-4E3C-A882-59CF7A4E93B6"}},"allowed":false}]}