{"@class":"TimeLineScript","id":{"uuid":"7B7C69A7-1DF0-4BAB-978C-42DDFE51578E"},"name":"TimeLineScript","enableOnAwake":false,"loop":false,"jumpToFirstFrameAtEnd":false,"speed":1.0,"weight":1.0,"loopStartTime":0,"loopDuration":0,"is_imported":false,"type":"user","scripts":{"@class":"StdListRuntimeScript","list":[{"@class":"AnimationScript","id":{"uuid":"16AF1A3B-6C29-4394-AB9A-7050BB6991E7"},"name":"AnimationScript","enableOnAwake":false,"OwnerLink":{"@class":"BindingLink","targetId":{"uuid":"322731ED-162A-481B-84DD-B9C6B51DC407"},"targetRelativeAddress":{"@class":"NodeRelativeAddressBase","index":2,"name":"Ligthing-1","subaddress":{"@class":"NodeRelativeAddressBase","index":3,"name":"HelmetLighting:Lighting"}}},"animation":{"uuid":"F9D51555-AA1C-4217-BA27-0DC7DA2157F9"},"AnimationType":"object3D","is_imported":false,"isEnabled":true}]},"triggers":[{"@class":"AnimationTrigger","id":{"uuid":"AFF3B355-4452-469E-982E-73B3CA60FF72"},"ownerScriptId":{"uuid":"7B7C69A7-1DF0-4BAB-978C-42DDFE51578E"},"logicOperation":0,"resultType":0,"isInverted":false,"event":1,"bindingLink":{"@class":"BindingLink","targetId":{"uuid":"CFD19FED-55C0-46CB-82D5-D1E19AAE9BAE"}}}]}