{"@class":"TimeLineScript","id":{"uuid":"7EB06A07-93B8-46B2-A975-CC1D02A821F1"},"name":"TimeLineScript","enableOnAwake":false,"loop":false,"jumpToFirstFrameAtEnd":false,"speed":1.0,"weight":1.0,"loopStartTime":0,"loopDuration":0,"is_imported":false,"type":"user","scripts":{"@class":"StdListRuntimeScript","list":[{"@class":"AnimationScript","id":{"uuid":"544D81C9-5E1A-411C-A9D6-740F7EF60C3C"},"name":"AnimationScript","enableOnAwake":false,"OwnerLink":{"@class":"BindingLink","targetId":{"uuid":"1D4BB629-703F-4058-98D5-D68FE478C18F"},"targetRelativeAddress":{"@class":"NodeRelativeAddressBase","index":7,"name":"Shooter Rifle 01","subaddress":{"@class":"NodeRelativeAddressBase","index":1,"name":"States","subaddress":{"@class":"NodeRelativeAddressBase","index":6,"name":"Aiming"}}}},"animation":{"uuid":"CA5EEB20-246F-4241-8023-7F54634A9F96"},"AnimationType":"object3D","is_imported":false,"isEnabled":true},{"@class":"AnimationScript","id":{"uuid":"76583073-75AF-4F12-B1E8-0126F7BE8B0D"},"name":"AnimationScript","enableOnAwake":false,"OwnerLink":{"@class":"BindingLink","targetId":{"uuid":"2ED0CF73-072B-45CD-BCD4-16BD5473880B"},"targetRelativeAddress":{"@class":"NodeRelativeAddressBase","index":7,"name":"Shooter Rifle 01","subaddress":{"@class":"NodeRelativeAddressBase","index":1,"name":"States","subaddress":{"@class":"NodeRelativeAddressBase","index":9,"name":"Pursuing"}}}},"animation":{"uuid":"665E1D45-6FC6-41F5-8AC2-06889641A4D2"},"AnimationType":"object3D","is_imported":false,"isEnabled":true},{"@class":"AnimationScript","id":{"uuid":"9A0A4AEB-5BF6-4489-BFB1-3A97BB19BE56"},"name":"AnimationScript","enableOnAwake":false,"OwnerLink":{"@class":"BindingLink","targetId":{"uuid":"EE17CA07-C7FA-4245-B699-F3AEC7FA9274"},"targetRelativeAddress":{"@class":"NodeRelativeAddressBase","index":7,"name":"Shooter Rifle 01","subaddress":{"@class":"NodeRelativeAddressBase","index":0,"name":"Shooter","subaddress":{"@class":"NodeRelativeAddressBase","index":0,"name":"Sensors","subaddress":{"@class":"NodeRelativeAddressBase","index":7,"name":"Shooter_Front"}}}}},"animation":{"uuid":"D2DCC19A-77D6-4B87-BE4B-C41BD1AB7ADA"},"AnimationType":"object3D","is_imported":false,"isEnabled":true},{"@class":"AnimationScript","id":{"uuid":"F18F0C64-2A81-4326-B16B-9DD29B16BB86"},"name":"Annoy","enableOnAwake":false,"OwnerLink":{"@class":"BindingLink","targetId":{"uuid":"EC0F627F-B7D8-4F98-9231-66AE97E054CA"},"targetRelativeAddress":{"@class":"NodeRelativeAddressBase","index":7,"name":"Shooter Rifle 01","subaddress":{"@class":"NodeRelativeAddressBase","index":1,"name":"States","subaddress":{"@class":"NodeRelativeAddressBase","index":10,"name":"Annoy"}}}},"animation":{"uuid":"BD1FB8A7-093A-44A1-A972-414C56576736"},"AnimationType":"object3D","is_imported":false,"isEnabled":true},{"@class":"AnimationScript","id":{"uuid":"0EF4C1E2-AAA3-45E1-B809-9C6F92169157"},"name":"Shooting Stay","enableOnAwake":false,"OwnerLink":{"@class":"BindingLink","targetId":{"uuid":"15F03973-B25E-47BE-8D3E-15DB692FD43D"},"targetRelativeAddress":{"@class":"NodeRelativeAddressBase","index":7,"name":"Shooter Rifle 01","subaddress":{"@class":"NodeRelativeAddressBase","index":1,"name":"States","subaddress":{"@class":"NodeRelativeAddressBase","index":12,"name":"Shooting Stay"}}}},"animation":{"uuid":"FAFE13D3-DCCF-414B-AC08-EA275E6EA5C5"},"AnimationType":"object3D","is_imported":false,"isEnabled":true},{"@class":"AnimationScript","id":{"uuid":"D013655B-1DC2-4557-BBD4-0E906745714E"},"name":"Bot_Shooter_01","enableOnAwake":false,"OwnerLink":{"@class":"BindingLink","targetId":{"uuid":"11B8A3A6-2F29-4400-AD9A-20D8289D60F4"},"targetRelativeAddress":{"@class":"NodeRelativeAddressBase","index":7,"name":"Shooter Rifle 01"}},"animation":{"uuid":"7AC4F07C-F69E-42CB-A2ED-1084298FD0B0"},"AnimationType":"object3D","is_imported":false,"isEnabled":true},{"@class":"AnimationScript","id":{"uuid":"1B601700-3188-4C2B-9759-9BF07383C9CA"},"name":"Inserted animations","enableOnAwake":false,"OwnerLink":{"@class":"BindingLink"},"animation":{"uuid":"D1E6BAF0-CEBD-4CB5-B4A4-A993DC82B117"},"AnimationType":"timeline","is_imported":false,"isEnabled":true},{"@class":"AnimationScript","id":{"uuid":"EBAC3DF9-B52A-49A2-92D3-DE0C33C3898A"},"name":"Gun Sight","enableOnAwake":false,"OwnerLink":{"@class":"BindingLink","targetId":{"uuid":"7E1E4C78-ADE6-472C-813F-1E2139B5DFDB"},"targetRelativeAddress":{"@class":"NodeRelativeAddressBase","index":7,"name":"Shooter Rifle 01","subaddress":{"@class":"NodeRelativeAddressBase","index":0,"name":"Shooter","subaddress":{"@class":"NodeRelativeAddressBase","index":0,"name":"Sensors","subaddress":{"@class":"NodeRelativeAddressBase","index":1,"name":"Rifle Sight"}}}}},"animation":{"uuid":"B02D6B59-D43A-4582-B576-ED14D16A84D4"},"AnimationType":"object3D","is_imported":false,"isEnabled":true},{"@class":"AnimationScript","id":{"uuid":"22AFB212-5B05-4A6D-A5F2-B171303F03A4"},"name":"Aiming Zone","enableOnAwake":false,"OwnerLink":{"@class":"BindingLink","targetId":{"uuid":"AFE9F093-991C-4F8F-9F13-6BC281D65F50"},"targetRelativeAddress":{"@class":"NodeRelativeAddressBase","index":7,"name":"Shooter Rifle 01","subaddress":{"@class":"NodeRelativeAddressBase","index":0,"name":"Shooter","subaddress":{"@class":"NodeRelativeAddressBase","index":0,"name":"Sensors","subaddress":{"@class":"NodeRelativeAddressBase","index":9,"name":"Aiming Zone"}}}}},"animation":{"uuid":"A54AD5B4-EC6D-42AB-AB64-E1886160DFF6"},"AnimationType":"object3D","is_imported":false,"isEnabled":true},{"@class":"AnimationScript","id":{"uuid":"68BB1C4D-9433-424B-A132-F0614B666228"},"name":"Purse Zone","enableOnAwake":false,"OwnerLink":{"@class":"BindingLink","targetId":{"uuid":"B1B07BAF-E85A-4F41-8062-AF65119B53F0"},"targetRelativeAddress":{"@class":"NodeRelativeAddressBase","index":7,"name":"Shooter Rifle 01","subaddress":{"@class":"NodeRelativeAddressBase","index":0,"name":"Shooter","subaddress":{"@class":"NodeRelativeAddressBase","index":0,"name":"Sensors","subaddress":{"@class":"NodeRelativeAddressBase","index":10,"name":"Purse Zone"}}}}},"animation":{"uuid":"DD1362FA-71CF-4351-AAC3-23A152E4FB6A"},"AnimationType":"object3D","is_imported":false,"isEnabled":true},{"@class":"AnimationScript","id":{"uuid":"88AAFF1A-7BA3-4C6D-ABEF-72D8CDCAE450"},"name":"Main Charcater Below Or Above","enableOnAwake":false,"OwnerLink":{"@class":"BindingLink","targetId":{"uuid":"D6C8EB97-1054-41FC-8A42-38C5D72F7EEB"},"targetRelativeAddress":{"@class":"NodeRelativeAddressBase","index":7,"name":"Shooter Rifle 01","subaddress":{"@class":"NodeRelativeAddressBase","index":0,"name":"Shooter","subaddress":{"@class":"NodeRelativeAddressBase","index":0,"name":"Sensors","subaddress":{"@class":"NodeRelativeAddressBase","index":3,"name":"MC Below"}}}}},"animation":{"uuid":"5A02134F-9137-43A1-A63D-DA83AA2D4B65"},"AnimationType":"object3D","is_imported":false,"isEnabled":true},{"@class":"AnimationScript","id":{"uuid":"5FE1545E-C2FB-4786-A3FC-B841B73C50A9"},"name":"Barrier Detector","enableOnAwake":false,"OwnerLink":{"@class":"BindingLink","targetId":{"uuid":"794E4CE9-DFD8-4AAC-9768-055C09B40BAD"},"targetRelativeAddress":{"@class":"NodeRelativeAddressBase","index":0,"name":"Shooter Rifle 01","subaddress":{"@class":"NodeRelativeAddressBase","index":1,"name":"Shooter","subaddress":{"@class":"NodeRelativeAddressBase","index":0,"name":"Sensors","subaddress":{"@class":"NodeRelativeAddressBase","index":0,"name":"Barrier Detector"}}}}},"animation":{"uuid":"C3FC45BE-3139-4C4C-BCC2-5C47437C253A"},"AnimationType":"object3D","is_imported":false,"isEnabled":true},{"@class":"AnimationScript","id":{"uuid":"866CE24B-41EE-4554-98BD-D36EDED7554C"},"name":"Gravitation","enableOnAwake":false,"OwnerLink":{"@class":"BindingLink","targetId":{"uuid":"58A1285D-339D-4C01-ABE2-0306982AB302"},"targetRelativeAddress":{"@class":"NodeRelativeAddressBase","index":1,"name":"Shooter Rifle 01","subaddress":{"@class":"NodeRelativeAddressBase","index":1,"name":"States","subaddress":{"@class":"NodeRelativeAddressBase","index":3,"name":"Gravitation"}}}},"animation":{"uuid":"7CA63E06-92DA-4E60-8336-75C95BCC95D5"},"AnimationType":"object3D","is_imported":false,"isEnabled":true},{"@class":"AnimationScript","id":{"uuid":"51E64DB8-2086-4267-827B-07D09418A33E"},"name":"Beat","enableOnAwake":false,"OwnerLink":{"@class":"BindingLink","targetId":{"uuid":"7EC5ED75-C63F-4C7B-8911-37D615C4A10B"},"targetRelativeAddress":{"@class":"NodeRelativeAddressBase","index":7,"name":"Shooter Rifle 01","subaddress":{"@class":"NodeRelativeAddressBase","index":1,"name":"States","subaddress":{"@class":"NodeRelativeAddressBase","index":2,"name":"Beat"}}}},"animation":{"uuid":"AA7A828A-F332-4C7E-AFB9-9413DEA2B688"},"AnimationType":"object3D","is_imported":false,"isEnabled":false},{"@class":"AnimationScript","id":{"uuid":"3E0E4BAB-74E8-4CCA-9A6A-906FDEF567A1"},"name":"Shooting Crouching","enableOnAwake":false,"OwnerLink":{"@class":"BindingLink","targetId":{"uuid":"5FD3B8C7-6E82-492D-9962-A027317F4E54"},"targetRelativeAddress":{"@class":"NodeRelativeAddressBase","index":7,"name":"Shooter Rifle 01","subaddress":{"@class":"NodeRelativeAddressBase","index":1,"name":"States","subaddress":{"@class":"NodeRelativeAddressBase","index":13,"name":"Shooting Crouching"}}}},"animation":{"uuid":"CF8056B3-FADD-4935-AC64-00BCF1BDAA85"},"AnimationType":"object3D","is_imported":false,"isEnabled":true}]},"triggers":[{"@class":"AnimationTrigger","id":{"uuid":"61B9B1C5-EC93-4C29-B087-4758AD10BBD8"},"ownerScriptId":{"uuid":"7EB06A07-93B8-46B2-A975-CC1D02A821F1"},"logicOperation":0,"resultType":0,"isInverted":false,"event":2,"bindingLink":{"@class":"BindingLink","targetId":{"uuid":"F5220726-EBB8-4875-B1E5-0B522A8BB4B4"}}},{"@class":"CollisionTrigger","id":{"uuid":"864E3E6E-621F-4543-8089-719B39117958"},"ownerScriptId":{"uuid":"7EB06A07-93B8-46B2-A975-CC1D02A821F1"},"logicOperation":1,"resultType":0,"isInverted":false,"eventType":"inside","targetBindingLink":{"@class":"BindingLink","targetId":{"uuid":"25B45DCB-520C-4AA4-9B04-34F5AC994277"}},"zoneBindingLink":{"@class":"BindingLink","targetId":{"uuid":"25B45DCB-520C-4AA4-9B04-34F5AC994277"}},"allowed":true}]}