{"@class":"TimeLineScript","id":{"uuid":"8E32782E-FC4B-4333-BE4D-50441B36667E"},"name":"TimeLineScript","enableOnAwake":false,"loop":false,"jumpToFirstFrameAtEnd":false,"speed":1.0,"weight":1.0,"loopStartTime":0,"loopDuration":0,"is_imported":false,"type":"user","scripts":{"@class":"StdListRuntimeScript","list":[{"@class":"AnimationScript","id":{"uuid":"D97D724B-7B17-457D-B9DB-07426BA89F45"},"name":"AnimationScript","enableOnAwake":false,"OwnerLink":{"@class":"BindingLink","targetId":{"uuid":"CC5B46D3-CE5D-4C14-BCCC-6A9619A20916"},"targetRelativeAddress":{"@class":"NodeRelativeAddressBase","index":36,"name":"Case 10"}},"animation":{"uuid":"50B3E732-359B-4E54-9462-034EC94F2107"},"AnimationType":"object3D","is_imported":false,"isEnabled":true}]},"triggers":[{"@class":"AnimationTrigger","id":{"uuid":"604DA523-32F2-407F-8021-0F23CBC84BD1"},"ownerScriptId":{"uuid":"8E32782E-FC4B-4333-BE4D-50441B36667E"},"logicOperation":0,"resultType":0,"isInverted":false,"event":1,"bindingLink":{"@class":"BindingLink","targetId":{"uuid":"CA270876-AA82-47B8-8497-DEFDDE246134"}}}]}