{"@class":"TimeLineScript","id":{"uuid":"B632B792-2340-4DC7-8B4D-6FAE15CDDC05"},"name":"TimeLineScript","enableOnAwake":false,"loop":true,"jumpToFirstFrameAtEnd":false,"speed":1.0,"weight":1.0,"loopStartTime":0,"loopDuration":0,"is_imported":false,"type":"user","scripts":{"@class":"StdListRuntimeScript","list":[{"@class":"AnimationScript","id":{"uuid":"700E2A00-19BC-4469-911B-8F185C426B2B"},"name":"AnimationScript","enableOnAwake":false,"OwnerLink":{"@class":"BindingLink","targetId":{"uuid":"0E721EA1-5763-4F2B-A100-7CF939287E44"}},"animation":{"uuid":"BBCC98BE-EA28-4644-84D0-E1BF792BB038"},"AnimationType":"avar","is_imported":false,"isEnabled":true},{"@class":"AnimationScript","id":{"uuid":"6F3E29E1-83AA-4408-AD80-A853E0E6C2CF"},"name":"AnimationScript","enableOnAwake":false,"OwnerLink":{"@class":"BindingLink","targetId":{"uuid":"AEA54DB5-DE15-48C0-ABB0-87E89D9D12C1"},"targetRelativeAddress":{"@class":"NodeRelativeAddressBase","index":3,"name":"Ligthing-1","subaddress":{"@class":"NodeRelativeAddressBase","index":3,"name":"HelmetLighting:Lighting"}}},"animation":{"uuid":"13AB1526-7C73-4AFD-87A9-E2CBFC02C892"},"AnimationType":"object3D","is_imported":false,"isEnabled":true}]},"triggers":[{"@class":"AnimationTrigger","id":{"uuid":"D46C858A-0B18-4B48-9EAB-4D7B995BAC32"},"ownerScriptId":{"uuid":"B632B792-2340-4DC7-8B4D-6FAE15CDDC05"},"logicOperation":0,"resultType":0,"isInverted":false,"event":3,"bindingLink":{"@class":"BindingLink","targetId":{"uuid":"CFD19FED-55C0-46CB-82D5-D1E19AAE9BAE"}}}],"symbolTable":{"@class":"VariousSymbolTable","id":{"uuid":"C88F7E28-3A2A-41AE-973D-BBB01DF24198"},"variables":[{"@class":"VariantVariable","id":{"uuid":"0E721EA1-5763-4F2B-A100-7CF939287E44"},"name":"s","type":"float","value":62.0}]}}