{"@class":"TimeLineScript","id":{"uuid":"CB54D428-41D4-424B-8536-5490088696CD"},"name":"TimeLineScript","enableOnAwake":false,"loop":true,"jumpToFirstFrameAtEnd":false,"speed":1.0,"weight":1.0,"loopStartTime":0,"loopDuration":0,"is_imported":false,"type":"user","scripts":{"@class":"StdListRuntimeScript","list":[{"@class":"AnimationScript","id":{"uuid":"1603E8D1-F1A7-4BAE-8FFD-9419D2E10512"},"name":"AnimationScript","enableOnAwake":false,"OwnerLink":{"@class":"BindingLink","targetId":{"uuid":"0E721EA1-5763-4F2B-A100-7CF939287E44"}},"animation":{"uuid":"9A6020EF-F24B-4BDC-94A5-9CBC53FD86E1"},"AnimationType":"avar","is_imported":false,"isEnabled":true},{"@class":"AnimationScript","id":{"uuid":"A2C86C2F-F5F9-466B-AA74-950194DD4F90"},"name":"AnimationScript","enableOnAwake":false,"OwnerLink":{"@class":"BindingLink","targetId":{"uuid":"4413AFD5-E116-4765-9C2C-21B3CC9C397F"},"targetRelativeAddress":{"@class":"NodeRelativeAddressBase","index":6,"name":"Ligthing-1","subaddress":{"@class":"NodeRelativeAddressBase","index":3,"name":"HelmetLighting:Lighting"}}},"animation":{"uuid":"51A32A93-0DD6-4889-88F2-8A10202683CB"},"AnimationType":"object3D","is_imported":false,"isEnabled":true}]},"triggers":[{"@class":"AnimationTrigger","id":{"uuid":"81EAF449-C417-45C6-9C98-59CE3A35448A"},"ownerScriptId":{"uuid":"CB54D428-41D4-424B-8536-5490088696CD"},"logicOperation":0,"resultType":0,"isInverted":false,"event":3,"bindingLink":{"@class":"BindingLink","targetId":{"uuid":"214B0206-F767-462C-A527-6273ADA54C36"}}}],"symbolTable":{"@class":"VariousSymbolTable","id":{"uuid":"C88F7E28-3A2A-41AE-973D-BBB01DF24198"},"variables":[{"@class":"VariantVariable","id":{"uuid":"0E721EA1-5763-4F2B-A100-7CF939287E44"},"name":"s","type":"float","value":180.0}]}}