{"@class":"TimeLineScript","id":{"uuid":"D6EE8335-17CC-4EFE-AE4F-C6745FFD060C"},"name":"TimeLineScript","enableOnAwake":false,"loop":false,"jumpToFirstFrameAtEnd":false,"speed":1.0,"weight":1.0,"loopStartTime":0,"loopDuration":0,"is_imported":false,"type":"user","scripts":{"@class":"StdListRuntimeScript","list":[{"@class":"AnimationScript","id":{"uuid":"83CB283D-9BF3-462B-9FAA-23C6CBF97800"},"name":"AnimationScript","enableOnAwake":false,"OwnerLink":{"@class":"BindingLink","targetId":{"uuid":"A2BB2A48-8837-4534-9437-895AF60715D8"},"targetRelativeAddress":{"@class":"NodeRelativeAddressBase","index":7,"name":"HelmetLighting:Lighting 13"}},"animation":{"uuid":"90D1E721-8C63-4EAD-B1D4-43FFEFD64E9A"},"AnimationType":"object3D","is_imported":false,"isEnabled":true}]},"triggers":[{"@class":"AnimationTrigger","id":{"uuid":"A425E7B1-692D-4A6B-863A-73ED4EF919CA"},"ownerScriptId":{"uuid":"D6EE8335-17CC-4EFE-AE4F-C6745FFD060C"},"logicOperation":0,"resultType":0,"isInverted":false,"event":2,"bindingLink":{"@class":"BindingLink","targetId":{"uuid":"CA270876-AA82-47B8-8497-DEFDDE246134"}}}]}