{"@class":"TimeLineScript","id":{"uuid":"E5ADF4EA-5165-479B-88E2-4E3CD1163781"},"name":"TimeLineScript","enableOnAwake":false,"loop":false,"jumpToFirstFrameAtEnd":false,"speed":1.0,"weight":1.0,"loopStartTime":0,"loopDuration":0,"is_imported":false,"type":"user","scripts":{"@class":"StdListRuntimeScript","list":[{"@class":"AnimationScript","id":{"uuid":"6118F6FC-C655-4769-8B6C-B17748B2B566"},"name":"AnimationScript","enableOnAwake":false,"OwnerLink":{"@class":"BindingLink","targetId":{"uuid":"286DA2FB-36CA-47A3-8C86-2685ED38F645"},"targetRelativeAddress":{"@class":"NodeRelativeAddressBase","index":8,"name":"Ligthing-1","subaddress":{"@class":"NodeRelativeAddressBase","index":3,"name":"HelmetLighting:Lighting"}}},"animation":{"uuid":"E03954D0-D474-4B0D-945B-7F6FD7104CBC"},"AnimationType":"object3D","is_imported":false,"isEnabled":true}]},"triggers":[{"@class":"AnimationTrigger","id":{"uuid":"ED64D9A2-7C42-4A9E-9DA4-D2F3C59FEB2A"},"ownerScriptId":{"uuid":"E5ADF4EA-5165-479B-88E2-4E3CD1163781"},"logicOperation":0,"resultType":0,"isInverted":false,"event":2,"bindingLink":{"@class":"BindingLink","targetId":{"uuid":"AB5129E2-82FF-4353-8DE2-E1167EB8723A"}}}]}