{"@class":"TimeLineScript","id":{"uuid":"EEE31D24-9800-4B91-BA7A-33CFC7FC4365"},"name":"TimeLineScript","enableOnAwake":false,"loop":false,"jumpToFirstFrameAtEnd":false,"speed":1.0,"weight":1.0,"loopStartTime":0,"loopDuration":0,"is_imported":false,"type":"user","scripts":{"@class":"StdListRuntimeScript","list":[{"@class":"AnimationScript","id":{"uuid":"B404B3EB-90B3-4BBE-BA7A-65D1A676DCC6"},"name":"AnimationScript","enableOnAwake":false,"OwnerLink":{"@class":"BindingLink","targetId":{"uuid":"93044C2F-CA1E-4ECD-A857-C38142448CCE"},"targetRelativeAddress":{"@class":"NodeRelativeAddressBase","index":6,"name":"Ligthing-1","subaddress":{"@class":"NodeRelativeAddressBase","index":3,"name":"HelmetLighting:Lighting"}}},"animation":{"uuid":"1FDE0BF3-B29F-4B97-9863-90DD78D8B8F4"},"AnimationType":"object3D","is_imported":false,"isEnabled":true}]},"triggers":[{"@class":"AnimationTrigger","id":{"uuid":"5D562760-8647-4A23-AC07-78F28FB3E083"},"ownerScriptId":{"uuid":"EEE31D24-9800-4B91-BA7A-33CFC7FC4365"},"logicOperation":0,"resultType":0,"isInverted":false,"event":2,"bindingLink":{"@class":"BindingLink","targetId":{"uuid":"AB5129E2-82FF-4353-8DE2-E1167EB8723A"}}}]}