{"@class":"TimeLineScript","id":{"uuid":"EF8A349A-08E5-4AF5-968C-FD3B5CC9DCF6"},"name":"TimeLineScript","enableOnAwake":false,"loop":false,"jumpToFirstFrameAtEnd":false,"speed":1.0,"weight":1.0,"loopStartTime":0,"loopDuration":0,"is_imported":false,"type":"user","scripts":{"@class":"StdListRuntimeScript","list":[{"@class":"AnimationScript","id":{"uuid":"BA8C23D1-0D79-4175-8208-46F6F7BAEF23"},"name":"AnimationScript","enableOnAwake":false,"OwnerLink":{"@class":"BindingLink","targetId":{"uuid":"0888DE0F-4230-47FA-A83E-0C42DD0E5875"},"targetRelativeAddress":{"@class":"NodeRelativeAddressBase","index":27,"name":"HelmetLighting:Lighting 6"}},"animation":{"uuid":"39F736F6-1FEA-4D14-B1EB-19CA5749FE7E"},"AnimationType":"object3D","is_imported":false,"isEnabled":true}]},"triggers":[{"@class":"AnimationTrigger","id":{"uuid":"DB6C981B-A743-4860-ABC3-5CE6710508E9"},"ownerScriptId":{"uuid":"EF8A349A-08E5-4AF5-968C-FD3B5CC9DCF6"},"logicOperation":0,"resultType":0,"isInverted":false,"event":2,"bindingLink":{"@class":"BindingLink","targetId":{"uuid":"CA270876-AA82-47B8-8497-DEFDDE246134"}}}]}