{"@class":"TimeLineScript","id":{"uuid":"F1FE22BF-9433-4617-BAB4-B31D5D3B150E"},"name":"TimeLineScript","enableOnAwake":false,"loop":false,"jumpToFirstFrameAtEnd":false,"speed":1.0,"weight":1.0,"loopStartTime":0,"loopDuration":0,"is_imported":false,"type":"user","scripts":{"@class":"StdListRuntimeScript","list":[{"@class":"AnimationScript","id":{"uuid":"5E11457D-5B59-4EE0-9E9B-C94294E8B3AF"},"name":"AnimationScript","enableOnAwake":false,"OwnerLink":{"@class":"BindingLink","targetId":{"uuid":"7938380D-9B91-4E10-A74A-575B624EA9CB"},"targetRelativeAddress":{"@class":"NodeRelativeAddressBase","index":4,"name":"Ligthing-1","subaddress":{"@class":"NodeRelativeAddressBase","index":3,"name":"HelmetLighting:Lighting"}}},"animation":{"uuid":"745B2FB3-44DD-4DCB-A9B7-1F569E8141DC"},"AnimationType":"object3D","is_imported":false,"isEnabled":true}]},"triggers":[{"@class":"AnimationTrigger","id":{"uuid":"C2E6F393-EF16-431E-9FD2-F2E66F53F9BB"},"ownerScriptId":{"uuid":"F1FE22BF-9433-4617-BAB4-B31D5D3B150E"},"logicOperation":0,"resultType":0,"isInverted":false,"event":2,"bindingLink":{"@class":"BindingLink","targetId":{"uuid":"E53A51C6-3446-4B41-B1C5-659242BB9204"}}}]}