{"@class":"TimeLineScript","id":{"uuid":"F3176C37-101F-4D89-B2EB-4FE0C4151C80"},"name":"anim_jump","enableOnAwake":false,"loop":false,"jumpToFirstFrameAtEnd":false,"speed":1.0,"weight":1.0,"loopStartTime":0,"loopDuration":0,"is_imported":false,"type":"user","scripts":{"@class":"StdListRuntimeScript","list":[{"@class":"AnimationScript","id":{"uuid":"D09D6F9D-7464-44E1-810A-2EECEE3B73F1"},"name":"AnimationScript","enableOnAwake":false,"OwnerLink":{"@class":"BindingLink"},"animation":{"uuid":"129FA83A-7A01-4146-8B79-1F1B7DD5B2B4"},"AnimationType":"timeline","is_imported":false,"isEnabled":true}]},"triggers":[]}